{"frames": {

"Ojo0.png":
{
	"frame": {"x":0,"y":0,"w":400,"h":400},
	"rotated": false,
	"trimmed": false,
	"spriteSourceSize": {"x":0,"y":0,"w":400,"h":400},
	"sourceSize": {"w":400,"h":400},
	"pivot": {"x":0.5,"y":0.5}
},
"Ojo1.png":
{
	"frame": {"x":400,"y":0,"w":400,"h":400},
	"rotated": false,
	"trimmed": false,
	"spriteSourceSize": {"x":0,"y":0,"w":400,"h":400},
	"sourceSize": {"w":400,"h":400},
	"pivot": {"x":0.5,"y":0.5}
},
"Ojo2.png":
{
	"frame": {"x":800,"y":0,"w":400,"h":400},
	"rotated": false,
	"trimmed": false,
	"spriteSourceSize": {"x":0,"y":0,"w":400,"h":400},
	"sourceSize": {"w":400,"h":400},
	"pivot": {"x":0.5,"y":0.5}
},
"Ojo3.png":
{
	"frame": {"x":1200,"y":0,"w":400,"h":400},
	"rotated": false,
	"trimmed": false,
	"spriteSourceSize": {"x":0,"y":0,"w":400,"h":400},
	"sourceSize": {"w":400,"h":400},
	"pivot": {"x":0.5,"y":0.5}
},
"Ojo4.png":
{
	"frame": {"x":1600,"y":0,"w":400,"h":400},
	"rotated": false,
	"trimmed": false,
	"spriteSourceSize": {"x":0,"y":0,"w":400,"h":400},
	"sourceSize": {"w":400,"h":400},
	"pivot": {"x":0.5,"y":0.5}
},
"Ojo5.png":
{
	"frame": {"x":0,"y":400,"w":400,"h":400},
	"rotated": false,
	"trimmed": false,
	"spriteSourceSize": {"x":0,"y":0,"w":400,"h":400},
	"sourceSize": {"w":400,"h":400},
	"pivot": {"x":0.5,"y":0.5}
},
"Ojo6.png":
{
	"frame": {"x":400,"y":400,"w":400,"h":400},
	"rotated": false,
	"trimmed": false,
	"spriteSourceSize": {"x":0,"y":0,"w":400,"h":400},
	"sourceSize": {"w":400,"h":400},
	"pivot": {"x":0.5,"y":0.5}
},
"Ojo7.png":
{
	"frame": {"x":800,"y":400,"w":400,"h":400},
	"rotated": false,
	"trimmed": false,
	"spriteSourceSize": {"x":0,"y":0,"w":400,"h":400},
	"sourceSize": {"w":400,"h":400},
	"pivot": {"x":0.5,"y":0.5}
},
"Ojo8.png":
{
	"frame": {"x":1200,"y":400,"w":400,"h":400},
	"rotated": false,
	"trimmed": false,
	"spriteSourceSize": {"x":0,"y":0,"w":400,"h":400},
	"sourceSize": {"w":400,"h":400},
	"pivot": {"x":0.5,"y":0.5}
},
"Ojo9.png":
{
	"frame": {"x":1600,"y":400,"w":400,"h":400},
	"rotated": false,
	"trimmed": false,
	"spriteSourceSize": {"x":0,"y":0,"w":400,"h":400},
	"sourceSize": {"w":400,"h":400},
	"pivot": {"x":0.5,"y":0.5}
},
"Ojo10.png":
{
	"frame": {"x":0,"y":800,"w":400,"h":400},
	"rotated": false,
	"trimmed": false,
	"spriteSourceSize": {"x":0,"y":0,"w":400,"h":400},
	"sourceSize": {"w":400,"h":400},
	"pivot": {"x":0.5,"y":0.5}
},
"Ojo11.png":
{
	"frame": {"x":400,"y":800,"w":400,"h":400},
	"rotated": false,
	"trimmed": false,
	"spriteSourceSize": {"x":0,"y":0,"w":400,"h":400},
	"sourceSize": {"w":400,"h":400},
	"pivot": {"x":0.5,"y":0.5}
},
"Ojo12.png":
{
	"frame": {"x":800,"y":800,"w":400,"h":400},
	"rotated": false,
	"trimmed": false,
	"spriteSourceSize": {"x":0,"y":0,"w":400,"h":400},
	"sourceSize": {"w":400,"h":400},
	"pivot": {"x":0.5,"y":0.5}
},
"Ojo13.png":
{
	"frame": {"x":1200,"y":800,"w":400,"h":400},
	"rotated": false,
	"trimmed": false,
	"spriteSourceSize": {"x":0,"y":0,"w":400,"h":400},
	"sourceSize": {"w":400,"h":400},
	"pivot": {"x":0.5,"y":0.5}
},
"Ojo14.png":
{
	"frame": {"x":1600,"y":800,"w":400,"h":400},
	"rotated": false,
	"trimmed": false,
	"spriteSourceSize": {"x":0,"y":0,"w":400,"h":400},
	"sourceSize": {"w":400,"h":400},
	"pivot": {"x":0.5,"y":0.5}
},
"Ojo15.png":
{
	"frame": {"x":0,"y":1200,"w":400,"h":400},
	"rotated": false,
	"trimmed": false,
	"spriteSourceSize": {"x":0,"y":0,"w":400,"h":400},
	"sourceSize": {"w":400,"h":400},
	"pivot": {"x":0.5,"y":0.5}
},
"Ojo16.png":
{
	"frame": {"x":400,"y":1200,"w":400,"h":400},
	"rotated": false,
	"trimmed": false,
	"spriteSourceSize": {"x":0,"y":0,"w":400,"h":400},
	"sourceSize": {"w":400,"h":400},
	"pivot": {"x":0.5,"y":0.5}
},
"Ojo17.png":
{
	"frame": {"x":800,"y":1200,"w":400,"h":400},
	"rotated": false,
	"trimmed": false,
	"spriteSourceSize": {"x":0,"y":0,"w":400,"h":400},
	"sourceSize": {"w":400,"h":400},
	"pivot": {"x":0.5,"y":0.5}
},
"Ojo18.png":
{
	"frame": {"x":1200,"y":1200,"w":400,"h":400},
	"rotated": false,
	"trimmed": false,
	"spriteSourceSize": {"x":0,"y":0,"w":400,"h":400},
	"sourceSize": {"w":400,"h":400},
	"pivot": {"x":0.5,"y":0.5}
},
"Ojo19.png":
{
	"frame": {"x":1600,"y":1200,"w":400,"h":400},
	"rotated": false,
	"trimmed": false,
	"spriteSourceSize": {"x":0,"y":0,"w":400,"h":400},
	"sourceSize": {"w":400,"h":400},
	"pivot": {"x":0.5,"y":0.5}
},
"Ojo20.png":
{
	"frame": {"x":0,"y":1600,"w":400,"h":400},
	"rotated": false,
	"trimmed": false,
	"spriteSourceSize": {"x":0,"y":0,"w":400,"h":400},
	"sourceSize": {"w":400,"h":400},
	"pivot": {"x":0.5,"y":0.5}
},
"Ojo21.png":
{
	"frame": {"x":400,"y":1600,"w":400,"h":400},
	"rotated": false,
	"trimmed": false,
	"spriteSourceSize": {"x":0,"y":0,"w":400,"h":400},
	"sourceSize": {"w":400,"h":400},
	"pivot": {"x":0.5,"y":0.5}
},
"Ojo22.png":
{
	"frame": {"x":800,"y":1600,"w":400,"h":400},
	"rotated": false,
	"trimmed": false,
	"spriteSourceSize": {"x":0,"y":0,"w":400,"h":400},
	"sourceSize": {"w":400,"h":400},
	"pivot": {"x":0.5,"y":0.5}
},
"Ojo23.png":
{
	"frame": {"x":1200,"y":1600,"w":400,"h":400},
	"rotated": false,
	"trimmed": false,
	"spriteSourceSize": {"x":0,"y":0,"w":400,"h":400},
	"sourceSize": {"w":400,"h":400},
	"pivot": {"x":0.5,"y":0.5}
},
"Ojo24.png":
{
	"frame": {"x":1600,"y":1600,"w":400,"h":400},
	"rotated": false,
	"trimmed": false,
	"spriteSourceSize": {"x":0,"y":0,"w":400,"h":400},
	"sourceSize": {"w":400,"h":400},
	"pivot": {"x":0.5,"y":0.5}
}},
"meta": {
	"app": "http://www.codeandweb.com/texturepacker",
	"version": "1.0",
	"image": "ojo_desktop_1.png",
	"format": "RGBA8888",
	"size": {"w":2000,"h":2000},
	"scale": "1",
	"smartupdate": "$TexturePacker:SmartUpdate:7667126b6326bdecb2a0300a079de8a4:c1e3a824769482f47365023fe0209a1e:0f933de75ffdca9fff71e80259ccddfc$"
}
}
